{
    "combos": [
        {
            "caseSensitivity": 0,
            "creationDateTime": "2023-09-19T21:22:11.900",
            "description": "Logically equivalent",
            "enabled": true,
            "keyword": "´´leq",
            "matchingMode": 0,
            "modificationDateTime": "2024-09-26T12:15:12.851",
            "name": "",
            "snippet": "≡",
            "uuid": "{d0d3aa98-3746-4c0d-a625-712bb60840af}"
        },
        {
            "caseSensitivity": 0,
            "creationDateTime": "2023-09-19T21:35:32.159",
            "description": "",
            "enabled": true,
            "keyword": "´´not",
            "matchingMode": 0,
            "modificationDateTime": "2024-09-26T12:15:12.851",
            "name": "",
            "snippet": "￢",
            "uuid": "{7f8f0c5b-c8b1-43a0-9b3f-261236ffcd22}"
        },
        {
            "caseSensitivity": 0,
            "creationDateTime": "2023-09-19T21:36:17.691",
            "description": "exists\nexiste",
            "enabled": true,
            "keyword": "´´ex",
            "matchingMode": 0,
            "modificationDateTime": "2024-09-26T12:15:12.851",
            "name": "",
            "snippet": "∃",
            "uuid": "{ad28ec7e-5418-4032-97c5-26d0e2a83d74}"
        },
        {
            "caseSensitivity": 0,
            "creationDateTime": "2023-09-19T21:36:38.339",
            "description": "",
            "enabled": true,
            "keyword": "´´forall",
            "matchingMode": 0,
            "modificationDateTime": "2024-09-26T12:15:12.851",
            "name": "",
            "snippet": "∀",
            "uuid": "{8c2ddc54-de5e-42ab-96b0-937f97e60d79}"
        },
        {
            "caseSensitivity": 0,
            "creationDateTime": "2023-09-19T21:37:12.836",
            "description": "",
            "enabled": true,
            "keyword": "´´and",
            "matchingMode": 0,
            "modificationDateTime": "2024-09-26T12:15:12.851",
            "name": "",
            "snippet": "∧",
            "uuid": "{3ae3600b-61c5-4119-ad59-4193c4f20c2a}"
        },
        {
            "caseSensitivity": 0,
            "creationDateTime": "2023-09-19T21:37:39.725",
            "description": "",
            "enabled": true,
            "keyword": "´´or",
            "matchingMode": 0,
            "modificationDateTime": "2024-09-26T12:15:12.851",
            "name": "",
            "snippet": "∨",
            "uuid": "{5ffdda6c-513a-4859-9711-dcbfed94b891}"
        },
        {
            "caseSensitivity": 0,
            "creationDateTime": "2023-09-19T21:38:36.226",
            "description": "implies\nimplica",
            "enabled": true,
            "keyword": "´´imp",
            "matchingMode": 0,
            "modificationDateTime": "2024-09-26T12:15:12.853",
            "name": "",
            "snippet": "⇒",
            "uuid": "{e57c8bb1-58fb-412e-ac3c-cedf105b3a48}"
        },
        {
            "caseSensitivity": 0,
            "creationDateTime": "2023-09-19T21:39:07.366",
            "description": "does not exists\nno existe",
            "enabled": true,
            "keyword": "´´nex",
            "matchingMode": 0,
            "modificationDateTime": "2024-09-26T12:15:12.853",
            "name": "",
            "snippet": "∄",
            "uuid": "{81a360f4-5075-4e21-8e15-36ff97f3af1a}"
        },
        {
            "caseSensitivity": 0,
            "creationDateTime": "2023-09-19T21:41:52.462",
            "description": "",
            "enabled": true,
            "keyword": "´´iff",
            "matchingMode": 0,
            "modificationDateTime": "2024-09-26T12:15:12.853",
            "name": "",
            "snippet": "↔",
            "uuid": "{cf136bc0-60d7-4fb3-9e6f-e6e1fcf538b1}"
        },
        {
            "caseSensitivity": 0,
            "creationDateTime": "2023-09-19T21:43:45.332",
            "description": "",
            "enabled": true,
            "keyword": "´´nand",
            "matchingMode": 0,
            "modificationDateTime": "2024-09-26T12:15:12.853",
            "name": "",
            "snippet": "↑",
            "uuid": "{b8d89528-639c-4675-a989-dfc77e62238e}"
        },
        {
            "caseSensitivity": 0,
            "creationDateTime": "2023-09-19T21:59:35.725",
            "description": "",
            "enabled": true,
            "keyword": "´´per",
            "matchingMode": 0,
            "modificationDateTime": "2024-09-26T12:15:12.853",
            "name": "",
            "snippet": "∈",
            "uuid": "{cdaf53ae-b420-4c5d-b0dd-a72545ba0d94}"
        },
        {
            "caseSensitivity": 0,
            "creationDateTime": "2023-09-19T22:00:25.443",
            "description": "",
            "enabled": true,
            "keyword": "´´nper",
            "matchingMode": 0,
            "modificationDateTime": "2024-09-26T12:15:12.853",
            "name": "",
            "snippet": "∉",
            "uuid": "{dcfb42a7-1b9f-45dc-a2b1-f75c1637a7ec}"
        },
        {
            "caseSensitivity": 0,
            "creationDateTime": "2023-09-19T22:26:30.265",
            "description": "",
            "enabled": true,
            "keyword": "´´empty",
            "matchingMode": 0,
            "modificationDateTime": "2024-09-26T12:15:12.853",
            "name": "",
            "snippet": "Ø",
            "uuid": "{e2e5f5f9-563a-46bd-a221-0292114ce4ab}"
        },
        {
            "caseSensitivity": 0,
            "creationDateTime": "2023-09-19T22:29:27.062",
            "description": "",
            "enabled": true,
            "keyword": "´´cont>",
            "matchingMode": 0,
            "modificationDateTime": "2024-09-26T12:15:12.853",
            "name": "",
            "snippet": "⊃",
            "uuid": "{45180d1d-61de-434d-bf10-f58b2e338681}"
        },
        {
            "caseSensitivity": 0,
            "creationDateTime": "2023-09-19T22:30:37.743",
            "description": "",
            "enabled": true,
            "keyword": "´´cont<",
            "matchingMode": 0,
            "modificationDateTime": "2024-09-26T12:15:12.853",
            "name": "",
            "snippet": "⊂",
            "uuid": "{aed89419-f8ac-4903-b7c1-8d5ee99b22d2}"
        },
        {
            "caseSensitivity": 0,
            "creationDateTime": "2023-09-19T22:35:45.873",
            "description": "",
            "enabled": true,
            "keyword": "´´ncont<",
            "matchingMode": 0,
            "modificationDateTime": "2024-09-26T12:15:12.853",
            "name": "",
            "snippet": "⊄",
            "uuid": "{898af21d-b43d-4b96-81fc-b31b6a8b706d}"
        },
        {
            "caseSensitivity": 0,
            "creationDateTime": "2023-09-19T22:35:58.379",
            "description": "",
            "enabled": true,
            "keyword": "´´ncont>",
            "matchingMode": 0,
            "modificationDateTime": "2024-09-26T12:15:12.853",
            "name": "",
            "snippet": "⊅",
            "uuid": "{5f084752-1bbf-48f0-9e2e-07b0bcb7bd41}"
        },
        {
            "caseSensitivity": 0,
            "creationDateTime": "2023-09-19T22:47:32.484",
            "description": "",
            "enabled": true,
            "keyword": "´´union",
            "matchingMode": 0,
            "modificationDateTime": "2024-09-26T12:15:12.853",
            "name": "",
            "snippet": "∪",
            "uuid": "{35374650-d9fe-437e-a807-5aa09f03cba0}"
        },
        {
            "caseSensitivity": 0,
            "creationDateTime": "2023-09-19T22:47:59.675",
            "description": "",
            "enabled": true,
            "keyword": "´´inter",
            "matchingMode": 0,
            "modificationDateTime": "2024-09-26T12:15:12.854",
            "name": "",
            "snippet": "∩",
            "uuid": "{d011af3a-03f5-4a44-96d6-a7456c012858}"
        },
        {
            "caseSensitivity": 0,
            "creationDateTime": "2023-09-19T22:57:28.450",
            "description": "",
            "enabled": true,
            "keyword": "´´comp",
            "matchingMode": 0,
            "modificationDateTime": "2024-09-26T12:15:12.854",
            "name": "",
            "snippet": "ᶜ",
            "uuid": "{e676f396-392c-46f4-8475-98b91c20d716}"
        },
        {
            "caseSensitivity": 0,
            "creationDateTime": "2024-09-26T12:15:34.144",
            "description": "",
            "enabled": true,
            "keyword": "´´epsilon",
            "matchingMode": 0,
            "modificationDateTime": "2024-09-26T12:16:25.609",
            "name": "",
            "snippet": "ε",
            "uuid": "{e6feefc0-cefb-45bf-a547-698e93f3dcc7}"
        }
    ],
    "fileFormatVersion": 10,
    "groups": [
    ]
}
